{
  "JP": {
    "countryCode": "JP",
    "cityName": "東京",
    "tempC": 17,
    "humidity": 79,
    "weatherCode": 1,
    "asOf": "2026-05-12T08:00"
  },
  "US": {
    "countryCode": "US",
    "cityName": "ワシントンD.C.",
    "tempC": 14.9,
    "humidity": 57,
    "weatherCode": 0,
    "asOf": "2026-05-11T19:00"
  },
  "GB": {
    "countryCode": "GB",
    "cityName": "ロンドン",
    "tempC": 8.3,
    "humidity": 57,
    "weatherCode": 0,
    "asOf": "2026-05-12T00:00"
  },
  "DE": {
    "countryCode": "DE",
    "cityName": "ベルリン",
    "tempC": 8.6,
    "humidity": 81,
    "weatherCode": 3,
    "asOf": "2026-05-12T01:00"
  },
  "FR": {
    "countryCode": "FR",
    "cityName": "パリ",
    "tempC": 8.5,
    "humidity": 71,
    "weatherCode": 3,
    "asOf": "2026-05-12T01:00"
  },
  "CN": {
    "countryCode": "CN",
    "cityName": "北京",
    "tempC": 20,
    "humidity": 63,
    "weatherCode": 3,
    "asOf": "2026-05-12T07:00"
  },
  "KR": {
    "countryCode": "KR",
    "cityName": "ソウル",
    "tempC": 14.6,
    "humidity": 96,
    "weatherCode": 3,
    "asOf": "2026-05-12T08:00"
  },
  "IN": {
    "countryCode": "IN",
    "cityName": "ニューデリー",
    "tempC": 28,
    "humidity": 53,
    "weatherCode": 3,
    "asOf": "2026-05-12T04:30"
  },
  "BR": {
    "countryCode": "BR",
    "cityName": "ブラジリア",
    "tempC": 22.4,
    "humidity": 60,
    "weatherCode": 0,
    "asOf": "2026-05-11T20:00"
  },
  "AU": {
    "countryCode": "AU",
    "cityName": "キャンベラ",
    "tempC": 12.5,
    "humidity": 78,
    "weatherCode": 1,
    "asOf": "2026-05-12T09:00"
  }
}
