{
  "JP": {
    "countryCode": "JP",
    "cityName": "東京",
    "tempC": 11.1,
    "humidity": 59,
    "weatherCode": 2,
    "asOf": "2026-05-05T05:15"
  },
  "US": {
    "countryCode": "US",
    "cityName": "ワシントンD.C.",
    "tempC": 25.1,
    "humidity": 26,
    "weatherCode": 0,
    "asOf": "2026-05-04T16:15"
  },
  "GB": {
    "countryCode": "GB",
    "cityName": "ロンドン",
    "tempC": 14.7,
    "humidity": 76,
    "weatherCode": 3,
    "asOf": "2026-05-04T21:15"
  },
  "DE": {
    "countryCode": "DE",
    "cityName": "ベルリン",
    "tempC": 18.6,
    "humidity": 63,
    "weatherCode": 3,
    "asOf": "2026-05-04T22:15"
  },
  "FR": {
    "countryCode": "FR",
    "cityName": "パリ",
    "tempC": 16,
    "humidity": 83,
    "weatherCode": 61,
    "asOf": "2026-05-04T22:15"
  },
  "CN": {
    "countryCode": "CN",
    "cityName": "北京",
    "tempC": 15.7,
    "humidity": 68,
    "weatherCode": 0,
    "asOf": "2026-05-05T04:15"
  },
  "KR": {
    "countryCode": "KR",
    "cityName": "ソウル",
    "tempC": 7.2,
    "humidity": 99,
    "weatherCode": 3,
    "asOf": "2026-05-05T05:15"
  },
  "IN": {
    "countryCode": "IN",
    "cityName": "ニューデリー",
    "tempC": 23,
    "humidity": 79,
    "weatherCode": 0,
    "asOf": "2026-05-05T01:45"
  },
  "BR": {
    "countryCode": "BR",
    "cityName": "ブラジリア",
    "tempC": 22.8,
    "humidity": 64,
    "weatherCode": 2,
    "asOf": "2026-05-04T17:15"
  },
  "AU": {
    "countryCode": "AU",
    "cityName": "キャンベラ",
    "tempC": 7.7,
    "humidity": 91,
    "weatherCode": 1,
    "asOf": "2026-05-05T06:15"
  }
}
