[
  {
    "id": "g1 Globo-0-criador-da-choquei.ghtml",
    "headline": "Habeas corpus não impede nova prisão: por que decisão do STJ não evitou preventiva de MC Ryan SP, MC Poze do Rodo e criador da Choquei",
    "sourceName": "g1 Globo",
    "sourceUrl": "https://g1.globo.com/sp/sao-paulo/noticia/2026/04/23/habeas-corpus-nao-impede-nova-prisao-por-que-decisao-do-stj-nao-evitou-preventiva-de-mc-ryan-sp-mc-poze-do-rodo-e-criador-da-choquei.ghtml",
    "publishedAt": "2026-04-23T21:25:04.000Z",
    "countryCode": "BR",
    "lang": "pt"
  },
  {
    "id": "g1 Globo-1-em-arraial-do-cabo.ghtml",
    "headline": "Princípio de incêndio em embarcação mobiliza resgate em Arraial do Cabo",
    "sourceName": "g1 Globo",
    "sourceUrl": "https://g1.globo.com/rj/regiao-dos-lagos/noticia/2026/04/23/principio-de-incendio-em-embarcacao-mobiliza-resgate-em-arraial-do-cabo.ghtml",
    "publishedAt": "2026-04-23T21:24:59.000Z",
    "countryCode": "BR",
    "lang": "pt"
  },
  {
    "id": "g1 Globo-2-s-ampliacao-acervo.ghtml",
    "headline": "MEC Livros terá acervo ampliado para 25 mil obras, diz ministro da Educação",
    "sourceName": "g1 Globo",
    "sourceUrl": "https://g1.globo.com/educacao/noticia/2026/04/23/mec-livros-ampliacao-acervo.ghtml",
    "publishedAt": "2026-04-23T21:24:50.000Z",
    "countryCode": "BR",
    "lang": "pt"
  },
  {
    "id": "g1 Globo-3-a-os-procedimentos.ghtml",
    "headline": "Lula fará retirada de queratose na cabeça e infiltração no punho nesta sexta; entenda os procedimentos",
    "sourceName": "g1 Globo",
    "sourceUrl": "https://g1.globo.com/saude/noticia/2026/04/23/lula-queratose-infiltracao-entenda-os-procedimentos.ghtml",
    "publishedAt": "2026-04-23T21:24:10.000Z",
    "countryCode": "BR",
    "lang": "pt"
  },
  {
    "id": "ANSA-17-d-abe0-633c2c4f16c9.html",
    "headline": "Meta effettuerà 8.000 licenziamenti a maggio, il 10% della forza lavoro",
    "sourceName": "ANSA",
    "sourceUrl": "https://www.ansa.it/sito/notizie/economia/2026/04/23/meta-effettuera-8.000-licenziamenti-a-maggio-il-10-della-forza-lavoro_6086d319-2586-407d-abe0-633c2c4f16c9.html",
    "publishedAt": "2026-04-23T21:22:42.000Z",
    "countryCode": "IT",
    "lang": "it"
  },
  {
    "id": "g1 Globo-4-em-ruas-de-uberaba.ghtml",
    "headline": "VÍDEO: Vaca corre atrás de pedestres em ruas de Uberaba",
    "sourceName": "g1 Globo",
    "sourceUrl": "https://g1.globo.com/mg/triangulo-mineiro/noticia/2026/04/23/video-vaca-corre-atras-de-pedestres-em-ruas-de-uberaba.ghtml",
    "publishedAt": "2026-04-23T21:22:30.000Z",
    "countryCode": "BR",
    "lang": "pt"
  },
  {
    "id": "g1 Globo-5-espanha-veja-video.ghtml",
    "headline": "Peruano fica gravemente ferido após levar chifrada de 35 centímetros em tourada na Espanha; veja vídeo",
    "sourceName": "g1 Globo",
    "sourceUrl": "https://g1.globo.com/mundo/noticia/2026/04/23/peruano-fica-gravemente-ferido-apos-levar-chifrada-de-35-centimetros-em-tourada-na-espanha-veja-video.ghtml",
    "publishedAt": "2026-04-23T21:21:35.000Z",
    "countryCode": "BR",
    "lang": "pt"
  },
  {
    "id": "ANSA-10-5-a90c-8d971dd9886d.html",
    "headline": "Trump ordina di distruggere le posamine iraniane, 'Hormuz sigillato'",
    "sourceName": "ANSA",
    "sourceUrl": "https://www.ansa.it/sito/notizie/mondo/2026/04/23/-trump-ordina-di-distruggere-le-posamine-iraniane-hormuz-sigillato_c395e0b2-6be3-4945-a90c-8d971dd9886d.html",
    "publishedAt": "2026-04-23T21:17:16.000Z",
    "countryCode": "IT",
    "lang": "it"
  },
  {
    "id": "The Guardian-15--anthony-albanese-ntwnfb",
    "headline": "Australia news live: Andrew Hastie says US alliance weakened Australia; Sri Lanka hackers steal millions owed to Australia",
    "sourceName": "The Guardian",
    "sourceUrl": "https://www.theguardian.com/australia-news/live/2026/apr/24/andrew-hastie-us-defence-ndis-reform-cuts-budget-gas-export-fuel-crisis-jim-chalmers-anthony-albanese-ntwnfb",
    "publishedAt": "2026-04-23T21:17:06.000Z",
    "countryCode": "GB",
    "lang": "en"
  },
  {
    "id": "g1 Globo-6-3-de-abril-de-2026.ghtml",
    "headline": "VÍDEOS: Jornal do Acre 1ª Edição desta quinta-feira, 23 de abril de 2026",
    "sourceName": "g1 Globo",
    "sourceUrl": "https://g1.globo.com/ac/acre/playlist/videos-jornal-do-acre-1-edicao-desta-quinta-feira-23-de-abril-de-2026.ghtml",
    "publishedAt": "2026-04-23T21:15:03.000Z",
    "countryCode": "BR",
    "lang": "pt"
  },
  {
    "id": "g1 Globo-7-as-no-sul-de-minas.ghtml",
    "headline": "Homem é condenado a 60 anos por matar ex-companheira a facadas no Sul de Minas",
    "sourceName": "g1 Globo",
    "sourceUrl": "https://g1.globo.com/mg/sul-de-minas/noticia/2026/04/23/homem-e-condenado-a-60-anos-por-matar-ex-companheira-a-facadas-no-sul-de-minas.ghtml",
    "publishedAt": "2026-04-23T21:14:23.000Z",
    "countryCode": "BR",
    "lang": "pt"
  },
  {
    "id": "NHK-1-424/k10015106881000.html",
    "headline": "トランプ大統領 機雷敷設の船舶攻撃の方針 協議実現は不透明",
    "sourceName": "NHK",
    "sourceUrl": "http://www3.nhk.or.jp/news/html/20260424/k10015106881000.html",
    "publishedAt": "2026-04-23T21:12:46.000Z",
    "countryCode": "JP",
    "lang": "ja"
  },
  {
    "id": "g1 Globo-8-taveis-na-caatinga.ghtml",
    "headline": "E-book produzido por estudantes da Univasf aborda práticas sustentáveis na Caatinga",
    "sourceName": "g1 Globo",
    "sourceUrl": "https://g1.globo.com/pe/petrolina-regiao/noticia/2026/04/23/e-book-produzido-por-estudantes-da-univasf-aborda-praticas-sustentaveis-na-caatinga.ghtml",
    "publishedAt": "2026-04-23T21:12:27.000Z",
    "countryCode": "BR",
    "lang": "pt"
  },
  {
    "id": "g1 Globo-9-o-e-franca-ao-vivo.ghtml",
    "headline": "EPTV2 - Ribeirão e Franca",
    "sourceName": "g1 Globo",
    "sourceUrl": "https://g1.globo.com/sp/ribeirao-preto-franca/ao-vivo/eptv-2-ribeirao-e-franca-ao-vivo.ghtml",
    "publishedAt": "2026-04-23T21:12:16.000Z",
    "countryCode": "BR",
    "lang": "pt"
  },
  {
    "id": "g1 Globo-10-ser-vice-de-flavio.ghtml",
    "headline": "Caiado diz que pode privatizar fatias da Petrobras e afasta possibilidade de ser vice de Flávio",
    "sourceName": "g1 Globo",
    "sourceUrl": "https://g1.globo.com/mg/minas-gerais/eleicoes/2026/noticia/2026/04/23/caiado-diz-que-pode-privatizar-fatias-da-petrobras-e-afasta-possibilidade-de-ser-vice-de-flavio.ghtml",
    "publishedAt": "2026-04-23T21:12:07.000Z",
    "countryCode": "BR",
    "lang": "pt"
  },
  {
    "id": "Al Jazeera-0-trike?traffic_source=rss",
    "headline": "Funeral held for journalist killed in targeted Israeli strike",
    "sourceName": "Al Jazeera",
    "sourceUrl": "https://www.aljazeera.com/video/newsfeed/2026/4/23/funeral-held-for-journalist-killed-in-targeted-israeli-strike?traffic_source=rss",
    "publishedAt": "2026-04-23T21:11:59.000Z",
    "countryCode": "QA",
    "lang": "en"
  },
  {
    "id": "g1 Globo-11-oiania-e-aparecida.ghtml",
    "headline": "Veja os locais de vacinação contra a gripe em Goiânia e Aparecida",
    "sourceName": "g1 Globo",
    "sourceUrl": "https://g1.globo.com/go/goias/noticia/2026/04/23/veja-os-locais-de-vacinacao-contra-a-gripe-em-goiania-e-aparecida.ghtml",
    "publishedAt": "2026-04-23T21:11:15.000Z",
    "countryCode": "BR",
    "lang": "pt"
  },
  {
    "id": "g1 Globo-12--e-danificar-casas.ghtml",
    "headline": "Piedade decreta situação de emergência após chuva de granizo destruir lavouras e danificar mais de 100 casas",
    "sourceName": "g1 Globo",
    "sourceUrl": "https://g1.globo.com/sp/sorocaba-jundiai/noticia/2026/04/23/piedade-decreta-situacao-de-emergencia-apos-chuva-de-granizo-destruir-lavouras-e-danificar-casas.ghtml",
    "publishedAt": "2026-04-23T21:10:32.000Z",
    "countryCode": "BR",
    "lang": "pt"
  },
  {
    "id": "g1 Globo-13-rao-preto-e-franca.ghtml",
    "headline": "Brazilian Bacon Day, hard xote, chorinho, teatro: as dicas do fim de semana na região de Ribeirão Preto e Franca",
    "sourceName": "g1 Globo",
    "sourceUrl": "https://g1.globo.com/sp/ribeirao-preto-franca/em-cena/noticia/2026/04/23/brazilian-bacon-day-hard-xote-chorinho-teatro-as-dicas-do-fim-de-semana-na-regiao-de-ribeirao-preto-e-franca.ghtml",
    "publishedAt": "2026-04-23T21:10:25.000Z",
    "countryCode": "BR",
    "lang": "pt"
  },
  {
    "id": "ANSA-5-7-bfed-266f84a6e019.html",
    "headline": "Femminicidio a Foggia, guardia giurata uccide la moglie a colpi di pistola",
    "sourceName": "ANSA",
    "sourceUrl": "https://www.ansa.it/sito/notizie/cronaca/2026/04/23/femminicidio-a-foggia-guardia-giurata-uccide-la-moglie-a-colpi-di-pistola_b03962f3-c295-4977-bfed-266f84a6e019.html",
    "publishedAt": "2026-04-23T21:10:01.000Z",
    "countryCode": "IT",
    "lang": "it"
  },
  {
    "id": "g1 Globo-14-iciar-sua-formacao.ghtml",
    "headline": "Cursos de Psicanálise: como estudar e iniciar sua formação",
    "sourceName": "g1 Globo",
    "sourceUrl": "https://g1.globo.com/pr/parana/especial-publicitario/instituto-especonhecimento-psicanalitico/noticia/2026/04/23/cursos-de-psicanalise-como-estudar-e-iniciar-sua-formacao.ghtml",
    "publishedAt": "2026-04-23T21:09:51.000Z",
    "countryCode": "BR",
    "lang": "pt"
  },
  {
    "id": "NHK-2-424/k10015106821000.html",
    "headline": "後発地震注意情報 三陸沖で地震活動続く 震度1以上は28回発生",
    "sourceName": "NHK",
    "sourceUrl": "http://www3.nhk.or.jp/news/html/20260424/k10015106821000.html",
    "publishedAt": "2026-04-23T21:09:05.000Z",
    "countryCode": "JP",
    "lang": "ja"
  },
  {
    "id": "g1 Globo-15--vendo-estou-presa.ghtml",
    "headline": "Brasileira é condenada por tráfico na França e vídeo gravado antes da prisão viraliza: 'Se estiverem vendo, estou presa'",
    "sourceName": "g1 Globo",
    "sourceUrl": "https://g1.globo.com/sc/santa-catarina/noticia/2026/04/23/brasileira-condenada-trafico-franca-video-antes-prisao-viraliza-se-estiverem-vendo-estou-presa.ghtml",
    "publishedAt": "2026-04-23T21:09:00.000Z",
    "countryCode": "BR",
    "lang": "pt"
  },
  {
    "id": "g1 Globo-16-racicaba-neste-ano.ghtml",
    "headline": "Internações por gripe mais que dobram em Piracicaba neste ano",
    "sourceName": "g1 Globo",
    "sourceUrl": "https://g1.globo.com/sp/piracicaba-regiao/noticia/2026/04/23/internacoes-por-gripe-mais-que-dobram-em-piracicaba-neste-ano.ghtml",
    "publishedAt": "2026-04-23T21:07:50.000Z",
    "countryCode": "BR",
    "lang": "pt"
  },
  {
    "id": "g1 Globo-17--tigrinho-em-avare.ghtml",
    "headline": "Polícia prende duas pessoas e apreende seis veículos em operação contra 'jogos do tigrinho' em Avaré",
    "sourceName": "g1 Globo",
    "sourceUrl": "https://g1.globo.com/sp/itapetininga-regiao/noticia/2026/04/23/policia-prende-duas-pessoas-e-apreende-seis-veiculos-em-operacao-contra-jogos-do-tigrinho-em-avare.ghtml",
    "publishedAt": "2026-04-23T21:05:13.000Z",
    "countryCode": "BR",
    "lang": "pt"
  },
  {
    "id": "g1 Globo-18-inite-diz-planalto.ghtml",
    "headline": "Lula fará retirada de acúmulo de pele e infiltração no punho para tratar tendinite, diz Planalto",
    "sourceName": "g1 Globo",
    "sourceUrl": "https://g1.globo.com/politica/noticia/2026/04/23/lula-passara-por-procedimento-para-retirada-de-ceratose-e-infiltracao-em-punho-para-tratar-tendinite-diz-planalto.ghtml",
    "publishedAt": "2026-04-23T21:04:03.000Z",
    "countryCode": "BR",
    "lang": "pt"
  },
  {
    "id": "Al Jazeera-1-ussia?traffic_source=rss",
    "headline": "EU formally approves 90bn euro Ukraine loan and new sanctions on Russia",
    "sourceName": "Al Jazeera",
    "sourceUrl": "https://www.aljazeera.com/news/2026/4/23/eu-formally-approves-90bn-euro-ukraine-loan-and-new-sanctions-on-russia?traffic_source=rss",
    "publishedAt": "2026-04-23T21:03:10.000Z",
    "countryCode": "QA",
    "lang": "en"
  },
  {
    "id": "The Guardian-25-ade-ships-latest-updates",
    "headline": "Middle East crisis live: Trump orders navy to attack any boats laying mines in strait of Hormuz",
    "sourceName": "The Guardian",
    "sourceUrl": "https://www.theguardian.com/world/live/2026/apr/23/middle-east-crisis-live-news-us-iran-ceasefire-strait-of-hormuz-blockade-ships-latest-updates",
    "publishedAt": "2026-04-23T21:02:46.000Z",
    "countryCode": "GB",
    "lang": "en"
  },
  {
    "id": "Al Jazeera-2--pets?traffic_source=rss",
    "headline": "Pope decries migrants and refugees being treated ‘worse than house pets’",
    "sourceName": "Al Jazeera",
    "sourceUrl": "https://www.aljazeera.com/news/2026/4/23/pope-decries-migrants-and-refugees-being-treated-worse-than-house-pets?traffic_source=rss",
    "publishedAt": "2026-04-23T21:01:50.000Z",
    "countryCode": "QA",
    "lang": "en"
  },
  {
    "id": "g1 Globo-19-retaria-de-turismo.ghtml",
    "headline": "Daniel Oliveira desiste de candidatura e volta à Secretaria de Turismo do PI; 19 dias após exoneração",
    "sourceName": "g1 Globo",
    "sourceUrl": "https://g1.globo.com/pi/piaui/noticia/2026/04/23/daniel-oliveira-secretaria-de-turismo.ghtml",
    "publishedAt": "2026-04-23T21:01:48.000Z",
    "countryCode": "BR",
    "lang": "pt"
  },
  {
    "id": "g1 Globo-20-ista-bolsa-nos-eua.ghtml",
    "headline": "Jovem maranhense que atuou com refugiados conquista bolsa nos EUA",
    "sourceName": "g1 Globo",
    "sourceUrl": "https://g1.globo.com/ma/maranhao/vem-ver-pequeno/noticia/2026/04/23/jovem-maranhense-que-atuou-com-refugiados-conquista-bolsa-nos-eua.ghtml",
    "publishedAt": "2026-04-23T21:01:02.000Z",
    "countryCode": "BR",
    "lang": "pt"
  },
  {
    "id": "Al Jazeera-3-urers?traffic_source=rss",
    "headline": "War-driven demand boosts profits for weapons and aircraft manufacturers",
    "sourceName": "Al Jazeera",
    "sourceUrl": "https://www.aljazeera.com/economy/2026/4/23/war-driven-demand-boosts-profits-for-weapons-and-aircraft-manufacturers?traffic_source=rss",
    "publishedAt": "2026-04-23T21:00:40.000Z",
    "countryCode": "QA",
    "lang": "en"
  },
  {
    "id": "g1 Globo-21-por-alunos-da-fazu.ghtml",
    "headline": "Todos os estágios da 91ª ExpoZebu serão ocupados por alunos da Fazu",
    "sourceName": "g1 Globo",
    "sourceUrl": "https://g1.globo.com/mg/triangulo-mineiro/especial-publicitario/abcz/expozebu/noticia/2026/04/23/todos-os-estagios-da-91a-expozebu-serao-ocupados-por-alunos-da-fazu.ghtml",
    "publishedAt": "2026-04-23T21:00:33.000Z",
    "countryCode": "BR",
    "lang": "pt"
  },
  {
    "id": "g1 Globo-22-cil-aponta-biologo.ghtml",
    "headline": "Assustada, raposinha-do-campo é resgatada em área urbana de Presidente Venceslau: ‘Muito dócil’, aponta biólogo",
    "sourceName": "g1 Globo",
    "sourceUrl": "https://g1.globo.com/sp/presidente-prudente-e-regiao/noticia/2026/04/23/assustada-raposinha-do-campo-e-resgatada-em-area-urbana-de-presidente-venceslau-muito-docil-aponta-biologo.ghtml",
    "publishedAt": "2026-04-23T21:00:29.000Z",
    "countryCode": "BR",
    "lang": "pt"
  },
  {
    "id": "g1 Globo-23-da-de-santos-video.ghtml",
    "headline": "Carro pega fogo em avenida de Santos; VÍDEO",
    "sourceName": "g1 Globo",
    "sourceUrl": "https://g1.globo.com/sp/santos-regiao/noticia/2026/04/23/carro-pega-fogo-em-avenida-de-santos-video.ghtml",
    "publishedAt": "2026-04-23T20:59:19.000Z",
    "countryCode": "BR",
    "lang": "pt"
  },
  {
    "id": "g1 Globo-24-ra-em-juiz-de-fora.ghtml",
    "headline": "Homem é condenado a 43 anos de prisão por asfixiar e esfaquear mais de 20 vezes a companheira em Juiz de Fora",
    "sourceName": "g1 Globo",
    "sourceUrl": "https://g1.globo.com/mg/zona-da-mata/noticia/2026/04/23/homem-e-condenado-a-43-anos-de-prisao-por-asfixiar-e-esfaquear-mais-de-20-vezes-a-companheira-em-juiz-de-fora.ghtml",
    "publishedAt": "2026-04-23T20:58:51.000Z",
    "countryCode": "BR",
    "lang": "pt"
  },
  {
    "id": "g1 Globo-25-is-em-campo-grande.ghtml",
    "headline": "Lei que proíbe mulheres trans em banheiros femininos gera debate nas redes sociais em Campo Grande",
    "sourceName": "g1 Globo",
    "sourceUrl": "https://g1.globo.com/ms/mato-grosso-do-sul/noticia/2026/04/23/lei-que-proibe-mulheres-trans-em-banheiros-femininos-gera-debate-nas-redes-sociais-em-campo-grande.ghtml",
    "publishedAt": "2026-04-23T20:58:46.000Z",
    "countryCode": "BR",
    "lang": "pt"
  },
  {
    "id": "The Hindu-0-cies/article70898633.ece",
    "headline": "State may witness close contests in many constituencies",
    "sourceName": "The Hindu",
    "sourceUrl": "https://www.thehindu.com/elections/tamil-nadu-assembly/state-may-witness-close-contests-in-many-constituencies/article70898633.ece",
    "publishedAt": "2026-04-23T20:58:24.000Z",
    "countryCode": "IN",
    "lang": "en"
  },
  {
    "id": "ANSA-16-2-af07-53ea6a3c9593.html",
    "headline": "Nuove tensioni, Ranieri all'addio. Insanabili le divergenze con Gasperini",
    "sourceName": "ANSA",
    "sourceUrl": "https://www.ansa.it/sito/notizie/sport/calcio/2026/04/23/roma-ranieri-vicini-alla-rottura-attesa-una-nota_e5099733-4027-4082-af07-53ea6a3c9593.html",
    "publishedAt": "2026-04-23T20:58:12.000Z",
    "countryCode": "IT",
    "lang": "it"
  },
  {
    "id": "g1 Globo-26-imado-em-r-200-mil.ghtml",
    "headline": "PM realiza a maior apreensão de drogas do ano em Petrópolis; prejuízo ao tráfico é estimado em R$ 200 mil",
    "sourceName": "g1 Globo",
    "sourceUrl": "https://g1.globo.com/rj/regiao-serrana/noticia/2026/04/23/pm-realiza-maior-apreensao-de-drogas-do-ano-em-petropolis-prejuizo-ao-trafico-e-estimado-em-r-200-mil.ghtml",
    "publishedAt": "2026-04-23T20:58:07.000Z",
    "countryCode": "BR",
    "lang": "pt"
  },
  {
    "id": "g1 Globo-27-eicoes-no-exterior.ghtml",
    "headline": "TSE aprova liberação de R$ 13 milhões para Itamaraty organizar eleições no exterior",
    "sourceName": "g1 Globo",
    "sourceUrl": "https://g1.globo.com/politica/eleicoes/2026/noticia/2026/04/23/tse-aprova-transferencia-de-r-13-milhoes-para-itamaraty-organizar-eleicoes-no-exterior.ghtml",
    "publishedAt": "2026-04-23T20:57:06.000Z",
    "countryCode": "BR",
    "lang": "pt"
  },
  {
    "id": "g1 Globo-28-xao-mateus-magrini.ghtml",
    "headline": "Justiça Federal decreta prisão preventiva de influenciadores Chrys Dias e Mateus Magrini; Débora Paixão terá prisão domiciliar",
    "sourceName": "g1 Globo",
    "sourceUrl": "https://g1.globo.com/sp/sorocaba-jundiai/noticia/2026/04/23/decreto-prisao-chrys-dias-debora-paixao-mateus-magrini.ghtml",
    "publishedAt": "2026-04-23T20:56:03.000Z",
    "countryCode": "BR",
    "lang": "pt"
  },
  {
    "id": "g1 Globo-29-obertura-eleitoral.ghtml",
    "headline": "Eleições 2026: TV Liberal e representantes de partidos definem regras e datas da cobertura eleitoral",
    "sourceName": "g1 Globo",
    "sourceUrl": "https://g1.globo.com/pa/para/eleicoes/2026/noticia/2026/04/23/eleicoes-2026-tv-liberal-e-representantes-de-partidos-definem-regras-e-datas-da-cobertura-eleitoral.ghtml",
    "publishedAt": "2026-04-23T20:55:51.000Z",
    "countryCode": "BR",
    "lang": "pt"
  },
  {
    "id": "Al Jazeera-4-flict?traffic_source=rss",
    "headline": "Will complex EU loan deal intensify conflict?",
    "sourceName": "Al Jazeera",
    "sourceUrl": "https://www.aljazeera.com/video/inside-story/2026/4/23/will-complex-eu-loan-deal-intensify-conflict?traffic_source=rss",
    "publishedAt": "2026-04-23T20:55:28.000Z",
    "countryCode": "QA",
    "lang": "en"
  },
  {
    "id": "Al Jazeera-5--iran?traffic_source=rss",
    "headline": "Trump says he is keeping Strait of Hormuz closed, not Iran",
    "sourceName": "Al Jazeera",
    "sourceUrl": "https://www.aljazeera.com/video/newsfeed/2026/4/23/trump-says-he-is-keeping-strait-of-hormuz-closed-not-iran?traffic_source=rss",
    "publishedAt": "2026-04-23T20:53:26.000Z",
    "countryCode": "QA",
    "lang": "en"
  },
  {
    "id": "Al Jazeera-6-links?traffic_source=rss",
    "headline": "US sanctions Cambodian senator over purported scam network links",
    "sourceName": "Al Jazeera",
    "sourceUrl": "https://www.aljazeera.com/news/2026/4/23/us-sanctions-cambodian-senator-over-purported-scam-network-links?traffic_source=rss",
    "publishedAt": "2026-04-23T20:52:48.000Z",
    "countryCode": "QA",
    "lang": "en"
  },
  {
    "id": "The Hindu-1-vice/article70897309.ece",
    "headline": "Fishers flag safety gaps, call for quick-response rescue service",
    "sourceName": "The Hindu",
    "sourceUrl": "https://www.thehindu.com/news/national/kerala/fishers-flag-safety-gaps-call-for-quick-response-rescue-service/article70897309.ece",
    "publishedAt": "2026-04-23T20:37:24.000Z",
    "countryCode": "IN",
    "lang": "en"
  },
  {
    "id": "DW-0-a=en-rss-en-all-1573-rdf",
    "headline": "Warner Bros shareholders greenlight sale to Paramount",
    "sourceName": "DW",
    "sourceUrl": "https://www.dw.com/en/warner-bros-shareholders-greenlight-sale-to-paramount/a-76917707?maca=en-rss-en-all-1573-rdf",
    "publishedAt": "2026-04-23T20:37:00.000Z",
    "countryCode": "DE",
    "lang": "en"
  },
  {
    "id": "Al Jazeera-7--soul?traffic_source=rss",
    "headline": "Iran dismisses Trump’s claim of leadership rift, says nation is ‘one soul’",
    "sourceName": "Al Jazeera",
    "sourceUrl": "https://www.aljazeera.com/news/2026/4/23/iran-dismisses-trumps-claim-of-leadership-rift-says-nation-is-one-soul?traffic_source=rss",
    "publishedAt": "2026-04-23T20:26:13.000Z",
    "countryCode": "QA",
    "lang": "en"
  },
  {
    "id": "ANSA-23-0-89af-eb28d7dd66ef.html",
    "headline": "Donna britannica sceglie di morire in una clinica svizzera dopo la perdita del figlio",
    "sourceName": "ANSA",
    "sourceUrl": "https://www.ansa.it/sito/notizie/mondo/2026/04/23/britannica-sceglie-di-morire-in-clinica-svizzera-dopo-la-perdita-del-figlio_31e21d6b-dc02-4270-89af-eb28d7dd66ef.html",
    "publishedAt": "2026-04-23T20:23:45.000Z",
    "countryCode": "IT",
    "lang": "it"
  },
  {
    "id": "NHK-6-424/k10015106751000.html",
    "headline": "ネコの慢性腎臓病 新たな治療薬の製造販売 国に承認申請へ",
    "sourceName": "NHK",
    "sourceUrl": "http://www3.nhk.or.jp/news/html/20260424/k10015106751000.html",
    "publishedAt": "2026-04-23T20:23:01.000Z",
    "countryCode": "JP",
    "lang": "ja"
  },
  {
    "id": "NHK-0-424/k10015106911000.html",
    "headline": "岩手 大槌町 山林火災延焼続く 住民の4分の1に避難指示",
    "sourceName": "NHK",
    "sourceUrl": "http://www3.nhk.or.jp/news/html/20260424/k10015106911000.html",
    "publishedAt": "2026-04-23T20:14:20.000Z",
    "countryCode": "JP",
    "lang": "ja"
  },
  {
    "id": "El País-5-espues-de-nombrarlo.html",
    "headline": "Murtra destituye al CEO de Movistar Plus un año después de nombrarlo",
    "sourceName": "El País",
    "sourceUrl": "https://elpais.com/economia/2026-04-23/murtra-cesa-al-ceo-de-movistar-plus-un-ano-despues-de-nombrarlo.html",
    "publishedAt": "2026-04-23T20:10:33.000Z",
    "countryCode": "ES",
    "lang": "es"
  },
  {
    "id": "ANSA-11-d-8bcc-8eb6bd8586f1.html",
    "headline": "Leone: 'Troppe vittime innocenti, non posso accettare le guerre'",
    "sourceName": "ANSA",
    "sourceUrl": "https://www.ansa.it/vaticano/notizie/2026/04/23/il-papa-proteggere-gli-innocenti-non-posso-accettare-la-guerra_0775cbf6-e7b3-4e5d-8bcc-8eb6bd8586f1.html",
    "publishedAt": "2026-04-23T20:00:53.000Z",
    "countryCode": "IT",
    "lang": "it"
  },
  {
    "id": "The Hindu-2-tion/article70898707.ece",
    "headline": "Post-SIR electorate drop drives turnout surge; votes remain steady compared to 2021 election",
    "sourceName": "The Hindu",
    "sourceUrl": "https://www.thehindu.com/news/national/tamil-nadu/post-sir-electorate-drop-drives-turnout-surge-votes-remain-steady-compared-to-2021-election/article70898707.ece",
    "publishedAt": "2026-04-23T20:00:19.000Z",
    "countryCode": "IN",
    "lang": "en"
  },
  {
    "id": "The Hindu-3-bers/article70898471.ece",
    "headline": "Despite heat, senior citizens step out to vote in large numbers",
    "sourceName": "The Hindu",
    "sourceUrl": "https://www.thehindu.com/news/cities/chennai/despite-heat-senior-citizens-step-out-to-vote-in-large-numbers/article70898471.ece",
    "publishedAt": "2026-04-23T19:57:37.000Z",
    "countryCode": "IN",
    "lang": "en"
  },
  {
    "id": "ANSA-6-9-90e5-57fdbcb6570c.html",
    "headline": "Madre e figlia morte avvelenate, c'è la conferma: 'Intossicazione da ricina'. Sequestrato il cellulare alla figlia Alice",
    "sourceName": "ANSA",
    "sourceUrl": "https://www.ansa.it/sito/notizie/cronaca/2026/04/23/morte-avvelenate-pm-acquisire-gli-ultimi-5-mesi-sul-telefonino-di-alice_61b11baf-3f02-4659-90e5-57fdbcb6570c.html",
    "publishedAt": "2026-04-23T19:56:59.000Z",
    "countryCode": "IT",
    "lang": "it"
  },
  {
    "id": "El País-10-el-caso-mascarillas.html",
    "headline": "Ha llegado la hora de los expertos",
    "sourceName": "El País",
    "sourceUrl": "https://elpais.com/videos/2026-04-23/ha-llegado-la-hora-de-los-expertos-en-el-juicio-por-el-caso-mascarillas.html",
    "publishedAt": "2026-04-23T19:56:06.000Z",
    "countryCode": "ES",
    "lang": "es"
  },
  {
    "id": "DW-1-a=en-rss-en-all-1573-rdf",
    "headline": "What is Europe's plan to secure the Strait of Hormuz?",
    "sourceName": "DW",
    "sourceUrl": "https://www.dw.com/en/what-is-europe-s-plan-to-secure-the-strait-of-hormuz/a-76911137?maca=en-rss-en-all-1573-rdf",
    "publishedAt": "2026-04-23T19:53:00.000Z",
    "countryCode": "DE",
    "lang": "en"
  },
  {
    "id": "The Hindu-4-gles/article70896513.ece",
    "headline": "Pahalgam, a year on: Resilience falters, tourism struggles",
    "sourceName": "The Hindu",
    "sourceUrl": "https://www.thehindu.com/news/national/jammu-and-kashmir/pahalgam-a-year-on-resilience-falters-tourism-struggles/article70896513.ece",
    "publishedAt": "2026-04-23T19:47:41.000Z",
    "countryCode": "IN",
    "lang": "en"
  },
  {
    "id": "The Hindu-5-ling/article70898631.ece",
    "headline": "Kancheepuram district sees over 87% polling",
    "sourceName": "The Hindu",
    "sourceUrl": "https://www.thehindu.com/news/national/tamil-nadu/kancheepuram-district-sees-over-87-polling/article70898631.ece",
    "publishedAt": "2026-04-23T19:46:07.000Z",
    "countryCode": "IN",
    "lang": "en"
  },
  {
    "id": "The Hindu-6-nout/article70898779.ece",
    "headline": "Stalin commends people of T.N. for record voter turnout",
    "sourceName": "The Hindu",
    "sourceUrl": "https://www.thehindu.com/news/national/tamil-nadu/stalin-commends-people-of-tn-for-record-voter-turnout/article70898779.ece",
    "publishedAt": "2026-04-23T19:44:37.000Z",
    "countryCode": "IN",
    "lang": "en"
  },
  {
    "id": "The Hindu-7-luru/article70896803.ece",
    "headline": "19-year-old worker kills newborn minutes after delivery in factory toilet in Bengaluru",
    "sourceName": "The Hindu",
    "sourceUrl": "https://www.thehindu.com/news/national/karnataka/19-year-old-worker-kills-newborn-minutes-after-delivery-in-factory-toilet-in-bengaluru/article70896803.ece",
    "publishedAt": "2026-04-23T19:43:49.000Z",
    "countryCode": "IN",
    "lang": "en"
  },
  {
    "id": "ANSA-12-e-97e1-83a46930d979.html",
    "headline": "Meloni sfida l'Ue: 'Serve coraggio, non escludo lo scostamento'",
    "sourceName": "ANSA",
    "sourceUrl": "https://www.ansa.it/sito/notizie/politica/2026/04/23/meloni-sulla-crisi-energetica-lue-deve-essere-piu-coraggiosa_9656c91a-b51a-492e-97e1-83a46930d979.html",
    "publishedAt": "2026-04-23T19:42:18.000Z",
    "countryCode": "IT",
    "lang": "it"
  },
  {
    "id": "NHK-5-424/k10015106801000.html",
    "headline": "白亜紀のタコは巨大な捕食者だったか 口の化石から推定 北大",
    "sourceName": "NHK",
    "sourceUrl": "http://www3.nhk.or.jp/news/html/20260424/k10015106801000.html",
    "publishedAt": "2026-04-23T19:39:45.000Z",
    "countryCode": "JP",
    "lang": "ja"
  },
  {
    "id": "The Hindu-8-nnel/article70898475.ece",
    "headline": "Bengaluru: Mental health session held for north-east division police personnel",
    "sourceName": "The Hindu",
    "sourceUrl": "https://www.thehindu.com/news/national/karnataka/mental-health-session-held-for-north-east-division-police-personnel/article70898475.ece",
    "publishedAt": "2026-04-23T19:38:53.000Z",
    "countryCode": "IN",
    "lang": "en"
  },
  {
    "id": "The Hindu-9-pper/article70897230.ece",
    "headline": "Anagha from Tirthahalli is second topper in SSLC exam-1",
    "sourceName": "The Hindu",
    "sourceUrl": "https://www.thehindu.com/news/national/karnataka/anagha-from-tirthahalli-stands-as-the-second-topper/article70897230.ece",
    "publishedAt": "2026-04-23T19:38:24.000Z",
    "countryCode": "IN",
    "lang": "en"
  },
  {
    "id": "The Hindu-10-2627/article70897794.ece",
    "headline": "Karnataka tobacco crop size cut to 56 million kg for 2026–27",
    "sourceName": "The Hindu",
    "sourceUrl": "https://www.thehindu.com/news/national/karnataka/karnataka-tobacco-crop-slashed-to-56-million-kg-for-202627/article70897794.ece",
    "publishedAt": "2026-04-23T19:37:31.000Z",
    "countryCode": "IN",
    "lang": "en"
  },
  {
    "id": "The Hindu-11-tors/article70898667.ece",
    "headline": "KSRTC issues summer advisory for drivers, conductors",
    "sourceName": "The Hindu",
    "sourceUrl": "https://www.thehindu.com/news/national/karnataka/ksrtc-issues-summer-advisory-for-drivers-conductors/article70898667.ece",
    "publishedAt": "2026-04-23T19:33:54.000Z",
    "countryCode": "IN",
    "lang": "en"
  },
  {
    "id": "ANSA-13-a-9963-27ae0256852e.html",
    "headline": "Valditara contestato in un istituto tecnico di Roma: \"Lei non è benvenuto qui\"",
    "sourceName": "ANSA",
    "sourceUrl": "https://www.ansa.it/sito/videogallery/italia/2026/04/23/valditara-contestato-in-un-istituto-tecnico-di-roma-lei-non-e-benvenuto-qui_f4fba9cc-3535-4bca-9963-27ae0256852e.html",
    "publishedAt": "2026-04-23T19:32:39.000Z",
    "countryCode": "IT",
    "lang": "it"
  },
  {
    "id": "El País-3-actada-por-pp-y-vox.html",
    "headline": "Zapatero tilda de “inconstitucional” y “discriminatoria” la prioridad nacional pactada por PP y Vox",
    "sourceName": "El País",
    "sourceUrl": "https://elpais.com/espana/elecciones-andalucia/2026-04-23/zapatero-tilda-de-inconstitucional-y-discriminatoria-la-prioridad-nacional-pactada-por-pp-y-vox.html",
    "publishedAt": "2026-04-23T19:32:02.000Z",
    "countryCode": "ES",
    "lang": "es"
  },
  {
    "id": "ANSA-9-2-b990-ef6bc330007c.html",
    "headline": "Solovyov insiste e attacca Mattarella, 'non sapete di cosa parlate'",
    "sourceName": "ANSA",
    "sourceUrl": "https://www.ansa.it/sito/notizie/mondo/2026/04/23/solovyov-insiste-e-attacca-mattarella-non-sapete-di-cosa-parlate-_f5e9fbf7-0d54-4312-b990-ef6bc330007c.html",
    "publishedAt": "2026-04-23T19:24:50.000Z",
    "countryCode": "IT",
    "lang": "it"
  },
  {
    "id": "ANSA-8-0-a1bf-6048f5587bfc.html",
    "headline": "Arriva il decreto Schillaci, i medici di famiglia dipendenti pubblici e perno delle case di comunità",
    "sourceName": "ANSA",
    "sourceUrl": "https://www.ansa.it/canale_saluteebenessere/notizie/sanita/2026/04/23/arriva-il-decreto-schillaci-medici-di-famiglia-dipendenti-pubblici_a196a437-1c42-4c60-a1bf-6048f5587bfc.html",
    "publishedAt": "2026-04-23T19:24:23.000Z",
    "countryCode": "IT",
    "lang": "it"
  },
  {
    "id": "The Hindu-12-ives/article70898934.ece",
    "headline": "Congress questions EC notice to Kharge, alleges ulterior motives",
    "sourceName": "The Hindu",
    "sourceUrl": "https://www.thehindu.com/news/national/congress-questions-ec-notice-to-kharge-alleges-ulterior-motives/article70898934.ece",
    "publishedAt": "2026-04-23T19:23:39.000Z",
    "countryCode": "IN",
    "lang": "en"
  },
  {
    "id": "El País-16-os-que-estar-listos.html",
    "headline": "Europa ensaya en Francia un conflicto a gran escala: “Tenemos que estar listos”",
    "sourceName": "El País",
    "sourceUrl": "https://elpais.com/internacional/2026-04-23/europa-ensaya-en-francia-un-conflicto-a-gran-escala-tenemos-que-estar-listos.html",
    "publishedAt": "2026-04-23T19:20:44.000Z",
    "countryCode": "ES",
    "lang": "es"
  },
  {
    "id": "Al Jazeera-8-ineup?traffic_source=rss",
    "headline": "Real Betis vs Real Madrid: La Liga – teams, start time, lineup",
    "sourceName": "Al Jazeera",
    "sourceUrl": "https://www.aljazeera.com/sports/2026/4/23/real-betis-vs-real-madrid-la-liga-teams-start-lineup?traffic_source=rss",
    "publishedAt": "2026-04-23T19:20:30.000Z",
    "countryCode": "QA",
    "lang": "en"
  },
  {
    "id": "The Guardian-26--by-strategy-born-of-war",
    "headline": "Trump may talk of regime infighting, but Iran seems united by strategy born of war",
    "sourceName": "The Guardian",
    "sourceUrl": "https://www.theguardian.com/world/2026/apr/23/trump-may-talk-of-regime-infighting-but-iran-seems-united-by-strategy-born-of-war",
    "publishedAt": "2026-04-23T19:18:13.000Z",
    "countryCode": "GB",
    "lang": "en"
  },
  {
    "id": "El País-9-al-juicio-de-abalos.html",
    "headline": "Las periciales sobre los contratos de mascarillas y los audios de Koldo llevan la bronca al juicio de Ábalos",
    "sourceName": "El País",
    "sourceUrl": "https://elpais.com/espana/2026-04-23/las-periciales-sobre-los-contratos-de-mascarillas-y-los-audios-de-koldo-llevan-la-bronca-al-juicio-de-abalos.html",
    "publishedAt": "2026-04-23T19:16:51.000Z",
    "countryCode": "ES",
    "lang": "es"
  },
  {
    "id": "The Hindu-13-s-99/article70897486.ece",
    "headline": "Veteran NCP leader T.P. Peethambharan turns 99",
    "sourceName": "The Hindu",
    "sourceUrl": "https://www.thehindu.com/news/national/kerala/veteran-politician-tp-peethambharan-turns-99/article70897486.ece",
    "publishedAt": "2026-04-23T19:12:37.000Z",
    "countryCode": "IN",
    "lang": "en"
  },
  {
    "id": "The Hindu-14-oots/article70898407.ece",
    "headline": "Scaling climate adaptation from policy to grassroots",
    "sourceName": "The Hindu",
    "sourceUrl": "https://www.thehindu.com/opinion/op-ed/scaling-climate-adaptation-from-policy-to-grassroots/article70898407.ece",
    "publishedAt": "2026-04-23T19:10:57.000Z",
    "countryCode": "IN",
    "lang": "en"
  },
  {
    "id": "El País-6-ey-en-la-maestranza.html",
    "headline": "Roca Rey sufre una cogida “muy grave” en La Maestranza",
    "sourceName": "El País",
    "sourceUrl": "https://elpais.com/cultura/2026-04-23/aparatosa-cogida-a-roca-rey-en-la-maestranza.html",
    "publishedAt": "2026-04-23T19:09:48.000Z",
    "countryCode": "ES",
    "lang": "es"
  },
  {
    "id": "Al Jazeera-9-ssent?traffic_source=rss",
    "headline": "How Trump’s Iran war is driving military dissent",
    "sourceName": "Al Jazeera",
    "sourceUrl": "https://www.aljazeera.com/video/the-take-2/2026/4/23/how-trumps-iran-war-is-driving-military-dissent?traffic_source=rss",
    "publishedAt": "2026-04-23T19:08:51.000Z",
    "countryCode": "QA",
    "lang": "en"
  },
  {
    "id": "The Hindu-15-kode/article70898077.ece",
    "headline": "Kerala fireworks tragedy: police search every inch as kin wait with bated breath",
    "sourceName": "The Hindu",
    "sourceUrl": "https://www.thehindu.com/news/national/kerala/kerala-fireworks-tragedy-the-killing-fields-of-mundathikode/article70898077.ece",
    "publishedAt": "2026-04-23T19:08:35.000Z",
    "countryCode": "IN",
    "lang": "en"
  },
  {
    "id": "The Hindu-16-bill/article70898567.ece",
    "headline": "BJP women cadre accuse Congress of blocking quota bill",
    "sourceName": "The Hindu",
    "sourceUrl": "https://www.thehindu.com/news/national/telangana/bjp-women-cadre-accuse-congress-of-blocking-quota-bill/article70898567.ece",
    "publishedAt": "2026-04-23T19:07:14.000Z",
    "countryCode": "IN",
    "lang": "en"
  },
  {
    "id": "The Hindu-17-ulse/article70898751.ece",
    "headline": "A season to try and understand the people’s pulse",
    "sourceName": "The Hindu",
    "sourceUrl": "https://www.thehindu.com/opinion/op-ed/a-season-to-try-and-understand-the-peoples-pulse/article70898751.ece",
    "publishedAt": "2026-04-23T19:05:07.000Z",
    "countryCode": "IN",
    "lang": "en"
  },
  {
    "id": "ANSA-18-a-b568-d58824c0d397.html",
    "headline": "Assolti Lucarelli jr e Apolloni dall'accusa di violenza sessuale",
    "sourceName": "ANSA",
    "sourceUrl": "https://www.ansa.it/sito/notizie/cronaca/2026/04/23/assolti-lucarelli-jr-e-apolloni-dallaccusa-di-violenza-sessuale-_beae75e2-66f5-4e9a-b568-d58824c0d397.html",
    "publishedAt": "2026-04-23T19:04:16.000Z",
    "countryCode": "IT",
    "lang": "it"
  },
  {
    "id": "Al Jazeera-10-files?traffic_source=rss",
    "headline": "US Department of Justice watchdog to probe release of Epstein files",
    "sourceName": "Al Jazeera",
    "sourceUrl": "https://www.aljazeera.com/news/2026/4/23/us-department-of-justice-watchdog-to-probe-release-of-epstein-files?traffic_source=rss",
    "publishedAt": "2026-04-23T19:03:18.000Z",
    "countryCode": "QA",
    "lang": "en"
  },
  {
    "id": "The Hindu-18--arm/article70893244.ece",
    "headline": "Recent hits give Malayalam film industry a shot in the arm",
    "sourceName": "The Hindu",
    "sourceUrl": "https://www.thehindu.com/news/national/kerala/recent-hits-give-malayalam-film-industry-a-shot-in-the-arm/article70893244.ece",
    "publishedAt": "2026-04-23T18:59:10.000Z",
    "countryCode": "IN",
    "lang": "en"
  },
  {
    "id": "Al Jazeera-11--next?traffic_source=rss",
    "headline": "US Senate passes ICE funding resolution after ‘vote-a-rama’: What’s next?",
    "sourceName": "Al Jazeera",
    "sourceUrl": "https://www.aljazeera.com/news/2026/4/23/us-senate-passes-ice-funding-resolution-after-vote-a-rama-whats-next?traffic_source=rss",
    "publishedAt": "2026-04-23T18:55:10.000Z",
    "countryCode": "QA",
    "lang": "en"
  },
  {
    "id": "ANSA-1-8-88da-64abd919c0e7.html",
    "headline": "Vince l'Italia, i ristoranti 'La Mafia' cambiano nome",
    "sourceName": "ANSA",
    "sourceUrl": "https://www.ansa.it/sito/notizie/mondo/2026/04/23/vince-litalia-i-ristoranti-la-mafia-cambiano-nome_e43ec2f3-160b-4d78-88da-64abd919c0e7.html",
    "publishedAt": "2026-04-23T18:54:10.000Z",
    "countryCode": "IT",
    "lang": "it"
  },
  {
    "id": "El País-15-s-inversiones-en-ia.html",
    "headline": "Meta despedirá a cerca de 8.000 personas, el 10% de su plantilla global, por el impacto de sus inversiones en IA",
    "sourceName": "El País",
    "sourceUrl": "https://elpais.com/economia/2026-04-23/meta-despedira-a-cerca-de-8000-personas-el-10-de-su-plantilla-global-por-el-impacto-de-sus-inversiones-en-ia.html",
    "publishedAt": "2026-04-23T18:51:04.000Z",
    "countryCode": "ES",
    "lang": "es"
  },
  {
    "id": "ANSA-0-8-8f8a-cdb1ef8ee319.html",
    "headline": "Il principe Louis compie otto anni, in un video gioca felice al mare",
    "sourceName": "ANSA",
    "sourceUrl": "https://www.ansa.it/sito/videogallery/mondo/2026/04/23/il-principe-louis-compie-otto-anni-in-un-video-gioca-felice-al-mare_f9752c68-43a4-4238-8f8a-cdb1ef8ee319.html",
    "publishedAt": "2026-04-23T18:49:45.000Z",
    "countryCode": "IT",
    "lang": "it"
  },
  {
    "id": "ANSA-7-2-bef0-6e24e00d2acd.html",
    "headline": "Monito di Mattarella per il 25 aprile, la legge del più forte è barbarie",
    "sourceName": "ANSA",
    "sourceUrl": "https://www.ansa.it/sito/notizie/politica/2026/04/23/mattarella-se-prevale-la-legge-del-piu-forte-e-barbarie-nella-vita-internazionale_f692575d-2109-4692-bef0-6e24e00d2acd.html",
    "publishedAt": "2026-04-23T18:48:21.000Z",
    "countryCode": "IT",
    "lang": "it"
  },
  {
    "id": "Al Jazeera-12-tract?traffic_source=rss",
    "headline": "South Africa president suspends police chief over $21m contract",
    "sourceName": "Al Jazeera",
    "sourceUrl": "https://www.aljazeera.com/news/2026/4/23/south-africa-president-suspends-police-chief-over-21m-contract?traffic_source=rss",
    "publishedAt": "2026-04-23T18:43:30.000Z",
    "countryCode": "QA",
    "lang": "en"
  },
  {
    "id": "The Hindu-19-lice/article70899074.ece",
    "headline": "BRS social media convener arrested by Kukatpally police",
    "sourceName": "The Hindu",
    "sourceUrl": "https://www.thehindu.com/news/cities/Hyderabad/brs-social-media-convener-arrested-by-kukatpally-police/article70899074.ece",
    "publishedAt": "2026-04-23T18:43:19.000Z",
    "countryCode": "IN",
    "lang": "en"
  },
  {
    "id": "The Hindu-20--row/article70896501.ece",
    "headline": "Troubled waters: A.P., T.N. fishermen embroiled in a row",
    "sourceName": "The Hindu",
    "sourceUrl": "https://www.thehindu.com/news/national/andhra-pradesh/troubled-waters-ap-tn-fishermen-embroiled-in-a-row/article70896501.ece",
    "publishedAt": "2026-04-23T18:43:02.000Z",
    "countryCode": "IN",
    "lang": "en"
  },
  {
    "id": "ANSA-21-5-aeb5-b44c5eab7225.html",
    "headline": "Slitta l'obbligo di assicurazione per i monopattini, si temono rincari",
    "sourceName": "ANSA",
    "sourceUrl": "https://www.ansa.it/canale_motori/notizie/istituzioni/2026/04/22/slitta-al-16-luglio-lobbligo-di-assicurazione-rc-per-i-monopattini_9f7bf271-f4f9-4745-aeb5-b44c5eab7225.html",
    "publishedAt": "2026-04-23T18:42:18.000Z",
    "countryCode": "IT",
    "lang": "it"
  },
  {
    "id": "The Hindu-21-tion/article70897468.ece",
    "headline": "Two Scheduled Tribe couples in Tamil Nadu exercise their franchise for the first time this election",
    "sourceName": "The Hindu",
    "sourceUrl": "https://www.thehindu.com/elections/tamil-nadu-assembly/two-scheduled-tribe-couples-exercise-their-franchise-for-the-first-time-this-election/article70897468.ece",
    "publishedAt": "2026-04-23T18:40:51.000Z",
    "countryCode": "IN",
    "lang": "en"
  },
  {
    "id": "France 24-0--after-journalist-killed",
    "headline": "Lebanon leaders accuse Israel of war crime after journalist killed",
    "sourceName": "France 24",
    "sourceUrl": "https://www.france24.com/en/lebanon-leaders-accuse-israel-of-war-crime-after-journalist-killed",
    "publishedAt": "2026-04-23T18:39:40.000Z",
    "countryCode": "FR",
    "lang": "en"
  },
  {
    "id": "France 24-1-return-iran-to-stone-age",
    "headline": "Israel defense minister says awaiting US green light to 'return Iran to Stone Age'",
    "sourceName": "France 24",
    "sourceUrl": "https://www.france24.com/en/israel-defense-minister-says-awaiting-us-green-light-to-return-iran-to-stone-age",
    "publishedAt": "2026-04-23T18:36:23.000Z",
    "countryCode": "FR",
    "lang": "en"
  }
]
